README.md
setup.py
pymacaron_dynamodb/__init__.py
pymacaron_dynamodb.egg-info/PKG-INFO
pymacaron_dynamodb.egg-info/SOURCES.txt
pymacaron_dynamodb.egg-info/dependency_links.txt
pymacaron_dynamodb.egg-info/not-zip-safe
pymacaron_dynamodb.egg-info/requires.txt
pymacaron_dynamodb.egg-info/top_level.txt
test/test.py
test/test_pep8.py