Metadata-Version: 1.1
Name: pymacaron-dynamodb
Version: 0.0.16
Summary: Serialize/Deserialize Swagger JSON objects to and from DynamoDB, with transactional writes
Home-page: https://github.com/pymacaron/pymacaron-dynamodb
Author: Erwan Lemonnier
Author-email: erwan@lemonnier.se
License: BSD
Platform: any
Classifier: Environment :: Web Environment
Classifier: Intended Audience :: Developers
Classifier: License :: OSI Approved :: BSD License
Classifier: Operating System :: OS Independent
Classifier: Programming Language :: Python
Classifier: Topic :: Internet :: WWW/HTTP :: Dynamic Content
Classifier: Topic :: Software Development :: Libraries :: Python Modules
